webdrivertools/__init__.py
webdrivertools/webdrivertools.py
webdrivertools-0.0.4.dist-info/LICENSE
webdrivertools-0.0.4.dist-info/METADATA
webdrivertools-0.0.4.dist-info/WHEEL
webdrivertools-0.0.4.dist-info/top_level.txt
webdrivertools-0.0.4.dist-info/RECORD
